{
  "users": [
    {
      "id": 1,
      "email": "whatever@email.com",
      "password": "$2a$10$ApcSC64Of5E0.cHqGHMtb.axfJ/IX12OcmIGL2KbebrX0TCIBLB4q",
      "name": "Christian",
      "created_at": "2026-01-28 19:04:57",
      "temp_password": "Connect@pipeline"
    },
    {
      "id": 2,
      "email": "c.daumer@texaswin.fr",
      "password": "$2a$10$hCeYq81l3h.nvDbqfE4AiedUfLcbRkh2fRXQInmYtpwL9cs15tG76",
      "name": "Christian",
      "created_at": "2026-01-30 10:17:46",
      "temp_password": "Cda@texaswin14"
    },
    {
      "id": 3,
      "email": "f.anis@texaswin.fr",
      "password": "$2a$10$H7YRu0GFOh8xwpcKwdhmD.SQP5S4ADWFZwe4BlUf.Z/oP9KLqdJNG",
      "name": "Fr\u00e9d\u00e9ric",
      "created_at": "2026-01-30 10:18:31",
      "temp_password": "Fan@texaswin2026"
    },
    {
      "id": 4,
      "email": "r.niddam@texaswin.fr",
      "password": "$2a$10$L6Np3kmWIHYX8DhdfJ3Qy.C5QeSal.R5DFZDofuGiaA2lP2fLwOR2",
      "name": "Roger",
      "created_at": "2026-01-30 10:19:18",
      "temp_password": "Rni@tw14"
    }
  ],
  "prospects": [
    {
      "id": 2,
      "name": "Antik Batik",
      "contact_name": "M. Couadau",
      "email": "",
      "phone": "",
      "status": "Devis",
      "setup_amount": 18100.0,
      "monthly_amount": 1637.0,
      "training_amount": 7445.0,
      "material_amount": 0.0,
      "chance_percent": 20,
      "assigned_to": "Roger",
      "next_action": null,
      "deadline": null,
      "quote_date": "2025-10-17",
      "notes": "",
      "user_id": 1,
      "created_at": "2026-01-29 14:58:07",
      "updated_at": "2026-01-29 17:33:07",
      "decision_maker": "M. Eurin (DAF)",
      "status_date": "2026-01-29",
      "annual_amount": 1736.0
    },
    {
      "id": 4,
      "name": "Atelier Tropezien",
      "contact_name": "",
      "email": "",
      "phone": "",
      "status": "Devis",
      "setup_amount": 5460.0,
      "monthly_amount": 1136.0,
      "training_amount": 4600.0,
      "material_amount": 0.0,
      "chance_percent": 20,
      "assigned_to": "Roger",
      "next_action": null,
      "deadline": null,
      "quote_date": "2025-10-21",
      "notes": "",
      "user_id": 1,
      "created_at": "2026-01-29 16:33:15",
      "updated_at": "2026-01-29 19:02:16",
      "decision_maker": "",
      "status_date": "2026-01-29",
      "annual_amount": 0.0
    },
    {
      "id": 5,
      "name": "Bachaa",
      "contact_name": "M. Fatrez",
      "email": "",
      "phone": "",
      "status": "Devis",
      "setup_amount": 1435.0,
      "monthly_amount": 480.0,
      "training_amount": 3300.0,
      "material_amount": 0.0,
      "chance_percent": 20,
      "assigned_to": "Roger",
      "next_action": null,
      "deadline": null,
      "quote_date": "2025-09-17",
      "notes": "",
      "user_id": 1,
      "created_at": "2026-01-29 16:35:43",
      "updated_at": "2026-01-29 16:35:43",
      "decision_maker": "",
      "status_date": "2026-01-29",
      "annual_amount": 0.0
    },
    {
      "id": 6,
      "name": "Barbara Bui",
      "contact_name": "Paul-Louis Michel",
      "email": "",
      "phone": "",
      "status": "Devis",
      "setup_amount": 22270.0,
      "monthly_amount": 3504.0,
      "training_amount": 16531.25,
      "material_amount": 0.0,
      "chance_percent": 20,
      "assigned_to": "Roger",
      "next_action": null,
      "deadline": null,
      "quote_date": "2025-12-03",
      "notes": "",
      "user_id": 1,
      "created_at": "2026-01-29 16:39:52",
      "updated_at": "2026-01-29 16:39:52",
      "decision_maker": "Direction coll\u00e9giale",
      "status_date": "2026-01-29",
      "annual_amount": 0.0
    },
    {
      "id": 7,
      "name": "Elande",
      "contact_name": "Ines Marechal",
      "email": "",
      "phone": "",
      "status": "Prospection",
      "setup_amount": 0.0,
      "monthly_amount": 0.0,
      "training_amount": 0.0,
      "material_amount": 0.0,
      "chance_percent": 20,
      "assigned_to": "Roger",
      "next_action": null,
      "deadline": null,
      "quote_date": "",
      "notes": "",
      "user_id": 1,
      "created_at": "2026-01-29 16:41:49",
      "updated_at": "2026-01-29 16:41:49",
      "decision_maker": "?",
      "status_date": "2026-01-29",
      "annual_amount": 0.0
    },
    {
      "id": 8,
      "name": "Elsa Esturgie",
      "contact_name": "Elsa Esturgie",
      "email": "",
      "phone": "",
      "status": "Devis",
      "setup_amount": 3160.0,
      "monthly_amount": 230.0,
      "training_amount": 3450.0,
      "material_amount": 0.0,
      "chance_percent": 20,
      "assigned_to": "Roger",
      "next_action": null,
      "deadline": null,
      "quote_date": "2025-10-03",
      "notes": "",
      "user_id": 1,
      "created_at": "2026-01-29 16:49:49",
      "updated_at": "2026-01-29 16:49:49",
      "decision_maker": "Elsa Esturgie",
      "status_date": "2026-01-29",
      "annual_amount": 0.0
    },
    {
      "id": 9,
      "name": "Follow Me",
      "contact_name": "Mme Boulanger",
      "email": "",
      "phone": "",
      "status": "Devis",
      "setup_amount": 1435.0,
      "monthly_amount": 400.0,
      "training_amount": 5500.0,
      "material_amount": 0.0,
      "chance_percent": 20,
      "assigned_to": "Roger",
      "next_action": null,
      "deadline": null,
      "quote_date": "2025-09-15",
      "notes": "",
      "user_id": 1,
      "created_at": "2026-01-29 16:52:05",
      "updated_at": "2026-01-29 16:52:05",
      "decision_maker": "",
      "status_date": "2026-01-29",
      "annual_amount": 0.0
    },
    {
      "id": 10,
      "name": "FAST MODE / MAX MILLA",
      "contact_name": "Nida Foca",
      "email": "",
      "phone": "",
      "status": "Devis",
      "setup_amount": 6025.0,
      "monthly_amount": 450.0,
      "training_amount": 0.0,
      "material_amount": 0.0,
      "chance_percent": 20,
      "assigned_to": "Roger",
      "next_action": null,
      "deadline": null,
      "quote_date": "2025-10-14",
      "notes": "",
      "user_id": 1,
      "created_at": "2026-01-29 16:54:09",
      "updated_at": "2026-01-29 16:54:09",
      "decision_maker": "",
      "status_date": "2026-01-29",
      "annual_amount": 0.0
    },
    {
      "id": 11,
      "name": "Filatures du Lion",
      "contact_name": "Martine Lorand",
      "email": "",
      "phone": "",
      "status": "Prospection",
      "setup_amount": 0.0,
      "monthly_amount": 0.0,
      "training_amount": 0.0,
      "material_amount": 0.0,
      "chance_percent": 20,
      "assigned_to": "Roger",
      "next_action": null,
      "deadline": null,
      "quote_date": "",
      "notes": "",
      "user_id": 1,
      "created_at": "2026-01-29 16:55:40",
      "updated_at": "2026-01-29 17:08:14",
      "decision_maker": "",
      "status_date": "2026-01-29",
      "annual_amount": 0.0
    },
    {
      "id": 12,
      "name": "Follow Me",
      "contact_name": "Sophie Boulanger",
      "email": "",
      "phone": "",
      "status": "Devis",
      "setup_amount": 1435.0,
      "monthly_amount": 0.0,
      "training_amount": 5500.0,
      "material_amount": 0.0,
      "chance_percent": 20,
      "assigned_to": "Roger",
      "next_action": null,
      "deadline": null,
      "quote_date": "2025-09-15",
      "notes": "",
      "user_id": 1,
      "created_at": "2026-01-29 16:58:41",
      "updated_at": "2026-01-29 16:58:41",
      "decision_maker": "",
      "status_date": "2026-01-29",
      "annual_amount": 400.0
    },
    {
      "id": 13,
      "name": "Homecore",
      "contact_name": "Rapha\u00eblle Berthier",
      "email": "",
      "phone": "",
      "status": "Devis",
      "setup_amount": 10626.0,
      "monthly_amount": 117.3,
      "training_amount": 7700.0,
      "material_amount": 0.0,
      "chance_percent": 20,
      "assigned_to": "Roger",
      "next_action": null,
      "deadline": null,
      "quote_date": "2025-06-19",
      "notes": "",
      "user_id": 1,
      "created_at": "2026-01-29 17:01:50",
      "updated_at": "2026-01-29 17:01:50",
      "decision_maker": "",
      "status_date": "2026-01-29",
      "annual_amount": 0.0
    },
    {
      "id": 14,
      "name": "Jamin Puech",
      "contact_name": "Narindra Raharison",
      "email": "",
      "phone": "",
      "status": "Devis",
      "setup_amount": 7175.0,
      "monthly_amount": 901.0,
      "training_amount": 8100.0,
      "material_amount": 0.0,
      "chance_percent": 20,
      "assigned_to": "Roger",
      "next_action": null,
      "deadline": null,
      "quote_date": "2025-10-23",
      "notes": "",
      "user_id": 1,
      "created_at": "2026-01-29 17:04:46",
      "updated_at": "2026-01-29 17:04:46",
      "decision_maker": "",
      "status_date": "2026-01-29",
      "annual_amount": 0.0
    },
    {
      "id": 15,
      "name": "JLL Studio / Auraeme",
      "contact_name": "",
      "email": "",
      "phone": "",
      "status": "Devis",
      "setup_amount": 3160.0,
      "monthly_amount": 425.5,
      "training_amount": 3450.0,
      "material_amount": 0.0,
      "chance_percent": 20,
      "assigned_to": "Roger",
      "next_action": null,
      "deadline": null,
      "quote_date": "2025-07-10",
      "notes": "",
      "user_id": 1,
      "created_at": "2026-01-29 17:10:35",
      "updated_at": "2026-01-29 19:10:38",
      "decision_maker": "",
      "status_date": "2026-01-29",
      "annual_amount": 0.0
    },
    {
      "id": 16,
      "name": "Karma Koma",
      "contact_name": "Sophie Mozziconacci",
      "email": "",
      "phone": "",
      "status": "Devis",
      "setup_amount": 13220.0,
      "monthly_amount": 2409.0,
      "training_amount": 11241.35,
      "material_amount": 0.0,
      "chance_percent": 20,
      "assigned_to": "Roger",
      "next_action": null,
      "deadline": null,
      "quote_date": "2025-12-10",
      "notes": "",
      "user_id": 1,
      "created_at": "2026-01-29 17:12:39",
      "updated_at": "2026-01-29 17:12:39",
      "decision_maker": "",
      "status_date": "2026-01-29",
      "annual_amount": 0.0
    },
    {
      "id": 17,
      "name": "Lison",
      "contact_name": "Mme Baum",
      "email": "",
      "phone": "",
      "status": "Devis",
      "setup_amount": 2010.0,
      "monthly_amount": 268.0,
      "training_amount": 3450.0,
      "material_amount": 0.0,
      "chance_percent": 20,
      "assigned_to": "Roger",
      "next_action": null,
      "deadline": null,
      "quote_date": "2025-10-03",
      "notes": "",
      "user_id": 1,
      "created_at": "2026-01-29 17:14:00",
      "updated_at": "2026-01-29 19:01:39",
      "decision_maker": "",
      "status_date": "2026-01-29",
      "annual_amount": 0.0
    },
    {
      "id": 18,
      "name": "Louise Micha",
      "contact_name": "",
      "email": "",
      "phone": "",
      "status": "Prospection",
      "setup_amount": 0.0,
      "monthly_amount": 0.0,
      "training_amount": 0.0,
      "material_amount": 0.0,
      "chance_percent": 20,
      "assigned_to": "Roger",
      "next_action": null,
      "deadline": null,
      "quote_date": "",
      "notes": "",
      "user_id": 1,
      "created_at": "2026-01-29 17:14:35",
      "updated_at": "2026-01-29 17:14:35",
      "decision_maker": "Louise Micha",
      "status_date": "2026-01-29",
      "annual_amount": 0.0
    },
    {
      "id": 19,
      "name": "Made In Sens",
      "contact_name": "Marie Chiche",
      "email": "",
      "phone": "",
      "status": "Perdu",
      "setup_amount": 7340.0,
      "monthly_amount": 1342.6,
      "training_amount": 6600.0,
      "material_amount": 0.0,
      "chance_percent": 20,
      "assigned_to": "Roger",
      "next_action": null,
      "deadline": null,
      "quote_date": "2025-06-17",
      "notes": "",
      "user_id": 1,
      "created_at": "2026-01-29 17:18:09",
      "updated_at": "2026-01-29 17:18:26",
      "decision_maker": "Marie Chiche",
      "status_date": "2026-01-29",
      "annual_amount": 1532.0
    },
    {
      "id": 20,
      "name": "Maio",
      "contact_name": "Mme Gabison",
      "email": "",
      "phone": "",
      "status": "Devis",
      "setup_amount": 1435.0,
      "monthly_amount": 400.0,
      "training_amount": 3300.0,
      "material_amount": 0.0,
      "chance_percent": 20,
      "assigned_to": "Roger",
      "next_action": null,
      "deadline": null,
      "quote_date": "2025-09-15",
      "notes": "",
      "user_id": 1,
      "created_at": "2026-01-29 18:19:15",
      "updated_at": "2026-01-29 18:19:15",
      "decision_maker": "",
      "status_date": "2026-01-29",
      "annual_amount": 0.0
    },
    {
      "id": 21,
      "name": "Maison Broussaud",
      "contact_name": "Aymeric Broussaud",
      "email": "",
      "phone": "",
      "status": "Perdu",
      "setup_amount": 5457.5,
      "monthly_amount": 1797.0,
      "training_amount": 6612.5,
      "material_amount": 0.0,
      "chance_percent": 20,
      "assigned_to": "Roger",
      "next_action": null,
      "deadline": null,
      "quote_date": "2025-11-17",
      "notes": "",
      "user_id": 1,
      "created_at": "2026-01-29 18:22:16",
      "updated_at": "2026-01-29 18:22:54",
      "decision_maker": "",
      "status_date": "2026-01-29",
      "annual_amount": 0.0
    },
    {
      "id": 22,
      "name": "Maison Guillemette",
      "contact_name": "Mathilde Kerhoas",
      "email": "",
      "phone": "",
      "status": "Devis",
      "setup_amount": 6612.5,
      "monthly_amount": 2327.3,
      "training_amount": 0.0,
      "material_amount": 0.0,
      "chance_percent": 20,
      "assigned_to": "Roger",
      "next_action": null,
      "deadline": null,
      "quote_date": "2025-07-10",
      "notes": "",
      "user_id": 1,
      "created_at": "2026-01-29 18:26:10",
      "updated_at": "2026-01-29 18:26:10",
      "decision_maker": "",
      "status_date": "2026-01-29",
      "annual_amount": 0.0
    },
    {
      "id": 23,
      "name": "Maison Saint Julien",
      "contact_name": "Mme Carr-Audibert",
      "email": "",
      "phone": "",
      "status": "Devis",
      "setup_amount": 1435.0,
      "monthly_amount": 468.0,
      "training_amount": 5500.0,
      "material_amount": 0.0,
      "chance_percent": 20,
      "assigned_to": "Roger",
      "next_action": null,
      "deadline": null,
      "quote_date": "2025-09-15",
      "notes": "",
      "user_id": 1,
      "created_at": "2026-01-29 18:27:51",
      "updated_at": "2026-01-29 18:27:51",
      "decision_maker": "",
      "status_date": "2026-01-29",
      "annual_amount": 0.0
    },
    {
      "id": 24,
      "name": "Maximila",
      "contact_name": "M. Zengin",
      "email": "",
      "phone": "",
      "status": "Devis",
      "setup_amount": 6025.0,
      "monthly_amount": 950.0,
      "training_amount": 4600.0,
      "material_amount": 0.0,
      "chance_percent": 20,
      "assigned_to": "Roger",
      "next_action": null,
      "deadline": null,
      "quote_date": "2025-10-10",
      "notes": "",
      "user_id": 1,
      "created_at": "2026-01-29 18:32:39",
      "updated_at": "2026-01-29 18:32:39",
      "decision_maker": "",
      "status_date": "2026-01-29",
      "annual_amount": 0.0
    },
    {
      "id": 25,
      "name": "Nitah",
      "contact_name": "Elise Dupuy",
      "email": "",
      "phone": "",
      "status": "Devis",
      "setup_amount": 2585.0,
      "monthly_amount": 556.0,
      "training_amount": 6612.5,
      "material_amount": 0.0,
      "chance_percent": 20,
      "assigned_to": "Roger",
      "next_action": null,
      "deadline": null,
      "quote_date": "2025-11-13",
      "notes": "",
      "user_id": 1,
      "created_at": "2026-01-29 18:34:22",
      "updated_at": "2026-01-29 18:59:44",
      "decision_maker": "",
      "status_date": "2026-01-29",
      "annual_amount": 0.0
    },
    {
      "id": 26,
      "name": "Parall\u00e8le Paris",
      "contact_name": "Maxime DELAMARRE",
      "email": "",
      "phone": "",
      "status": "Devis",
      "setup_amount": 8335.0,
      "monthly_amount": 879.0,
      "training_amount": 5175.0,
      "material_amount": 0.0,
      "chance_percent": 20,
      "assigned_to": "Roger",
      "next_action": null,
      "deadline": null,
      "quote_date": "2025-10-08",
      "notes": "",
      "user_id": 1,
      "created_at": "2026-01-29 18:38:42",
      "updated_at": "2026-01-29 18:38:42",
      "decision_maker": "",
      "status_date": "2026-01-29",
      "annual_amount": 0.0
    },
    {
      "id": 27,
      "name": "Sans-Arcidet",
      "contact_name": "Mme Myriam Sans-Arcidet",
      "email": "",
      "phone": "",
      "status": "Devis",
      "setup_amount": 4310.0,
      "monthly_amount": 460.0,
      "training_amount": 3450.0,
      "material_amount": 0.0,
      "chance_percent": 20,
      "assigned_to": "Roger",
      "next_action": null,
      "deadline": null,
      "quote_date": "2025-10-07",
      "notes": "",
      "user_id": 1,
      "created_at": "2026-01-29 18:41:07",
      "updated_at": "2026-01-29 18:41:07",
      "decision_maker": "",
      "status_date": "2026-01-29",
      "annual_amount": 0.0
    },
    {
      "id": 28,
      "name": "Val de Saire",
      "contact_name": "Jean-Luc HYVER",
      "email": "",
      "phone": "",
      "status": "Devis",
      "setup_amount": 3160.0,
      "monthly_amount": 586.0,
      "training_amount": 6612.5,
      "material_amount": 0.0,
      "chance_percent": 20,
      "assigned_to": "Roger",
      "next_action": null,
      "deadline": null,
      "quote_date": "2025-11-14",
      "notes": "",
      "user_id": 1,
      "created_at": "2026-01-29 18:44:01",
      "updated_at": "2026-01-29 18:44:01",
      "decision_maker": "",
      "status_date": "2026-01-29",
      "annual_amount": 586.0
    },
    {
      "id": 29,
      "name": "Val\u00e9rie Khalfon",
      "contact_name": "",
      "email": "",
      "phone": "",
      "status": "Devis",
      "setup_amount": 6575.0,
      "monthly_amount": 651.1,
      "training_amount": 0.0,
      "material_amount": 0.0,
      "chance_percent": 20,
      "assigned_to": "Roger",
      "next_action": null,
      "deadline": null,
      "quote_date": "2025-07-10",
      "notes": "",
      "user_id": 1,
      "created_at": "2026-01-29 18:46:45",
      "updated_at": "2026-01-29 18:46:45",
      "decision_maker": "",
      "status_date": "2026-01-29",
      "annual_amount": 0.0
    },
    {
      "id": 30,
      "name": "Wop",
      "contact_name": "",
      "email": "",
      "phone": "",
      "status": "Devis",
      "setup_amount": 1435.0,
      "monthly_amount": 536.0,
      "training_amount": 5500.0,
      "material_amount": 0.0,
      "chance_percent": 20,
      "assigned_to": "Roger",
      "next_action": null,
      "deadline": null,
      "quote_date": "2025-09-15",
      "notes": "",
      "user_id": 1,
      "created_at": "2026-01-29 18:48:37",
      "updated_at": "2026-01-29 18:48:37",
      "decision_maker": "",
      "status_date": "2026-01-29",
      "annual_amount": 0.0
    },
    {
      "id": 31,
      "name": "10,03,53",
      "contact_name": "Anna",
      "email": "",
      "phone": "",
      "status": "Devis",
      "setup_amount": 3160.0,
      "monthly_amount": 240.0,
      "training_amount": 3450.0,
      "material_amount": 0.0,
      "chance_percent": 20,
      "assigned_to": "Roger",
      "next_action": null,
      "deadline": null,
      "quote_date": "2025-10-15",
      "notes": "",
      "user_id": 1,
      "created_at": "2026-01-29 18:50:06",
      "updated_at": "2026-01-29 18:50:06",
      "decision_maker": "",
      "status_date": "2026-01-29",
      "annual_amount": 0.0
    },
    {
      "id": 32,
      "name": "Ango",
      "contact_name": "Gwen Chollet",
      "email": "",
      "phone": "",
      "status": "Devis",
      "setup_amount": 2920.0,
      "monthly_amount": 1046.0,
      "training_amount": 3875.0,
      "material_amount": 0.0,
      "chance_percent": 20,
      "assigned_to": "Roger",
      "next_action": null,
      "deadline": null,
      "quote_date": "2025-09-15",
      "notes": "",
      "user_id": 1,
      "created_at": "2026-01-30 08:41:33",
      "updated_at": "2026-01-30 08:42:32",
      "decision_maker": "",
      "status_date": "2026-01-30",
      "annual_amount": 0.0
    }
  ],
  "activities": [],
  "next_actions": [
    {
      "id": 1,
      "prospect_id": 2,
      "action_type": "Relance",
      "planned_date": "2026-01-29",
      "actor": "Roger",
      "completed": 1,
      "completed_date": "2026-01-29",
      "user_id": 1,
      "created_at": "2026-01-29 17:33:22",
      "completed_note": "Manifestment le projet est de nouveau sur les rails. Il trouve que l'abonnement est plus cher que l'achat de licences. \nMonsieur Couadau doit revenir vers Roger semain prochaine\n"
    },
    {
      "id": 2,
      "prospect_id": 2,
      "action_type": "Relance",
      "planned_date": "2026-02-05",
      "actor": "Roger",
      "completed": 0,
      "completed_date": null,
      "user_id": 1,
      "created_at": "2026-01-29 17:35:18",
      "completed_note": null
    }
  ],
  "status_history": [
    {
      "id": 9,
      "prospect_id": 19,
      "old_status": "Devis",
      "new_status": "Perdu",
      "status_date": "2026-01-29",
      "notes": "",
      "user_id": 1,
      "created_at": "2026-01-29 17:18:26"
    },
    {
      "id": 10,
      "prospect_id": 21,
      "old_status": "Devis",
      "new_status": "Perdu",
      "status_date": "2026-01-29",
      "notes": "",
      "user_id": 1,
      "created_at": "2026-01-29 18:22:54"
    }
  ]
}